swivel/__init__.py
swivel/abstracts/__init__.py
swivel/abstracts/deployed.py
swivel/abstracts/market_place.py
swivel/abstracts/swivel.py
swivel/abstracts/vault_tracker.py
swivel/constants/__init__.py
swivel/contracts/__init__.py
swivel/contracts/abi.py
swivel/contracts/bin.py
swivel/contracts/market_place.py
swivel/contracts/swivel.py
swivel/contracts/vault_tracker.py
swivel/helpers/__init__.py
swivel/mocks/__init__.py
swivel/mocks/abi.py
swivel/mocks/bin.py
swivel/tests/__init__.py
swivel/tests/conftest.py
swivel/tests/helpers.py
swivel/tests/market_place_test.py
swivel/tests/signer_test.py
swivel/tests/swivel_test.py
swivel/tests/vault_tracker_only_test.py
swivel/tests/w3_test.py
swivel/vendors/__init__.py
swivel/vendors/signer.py
swivel/vendors/w3.py
swivel-2.2.0.dist-info/LICENSE
swivel-2.2.0.dist-info/METADATA
swivel-2.2.0.dist-info/WHEEL
swivel-2.2.0.dist-info/top_level.txt
swivel-2.2.0.dist-info/RECORD
