Metadata-Version: 2.1
Name: swivel
Version: 2.2.0
Summary: A python library for interacting with the Swivel Finance Protocol
Home-page: https://github.com/Swivel-Finance/swivel-py
Author: Swivel Finance
Author-email: support@swivel.finance
Keywords: swivel,finance,ethereum,blockchain,defi,web3
Classifier: Development Status :: 5 - Production/Stable
Classifier: Programming Language :: Python :: 3
Classifier: License :: OSI Approved :: MIT License
Classifier: Operating System :: OS Independent
Requires-Python: >=3.7.3
License-File: LICENSE
Provides-Extra: test
Requires-Dist: pytest (==6.2.5) ; extra == 'test'
Requires-Dist: eth-tester (==0.5.0b4) ; extra == 'test'
Requires-Dist: web3 (==5.23.1) ; extra == 'test'
Requires-Dist: py-eth-sig-utils (==0.4.0) ; extra == 'test'
